check_versions.py
python_pvm-1.0.4.dist-info/METADATA
python_pvm-1.0.4.dist-info/WHEEL
python_pvm-1.0.4.dist-info/entry_points.txt
python_pvm-1.0.4.dist-info/top_level.txt
python_pvm-1.0.4.dist-info/RECORD
