Metadata-Version: 2.1
Name: python-pvm
Version: 1.0.4
Summary: A Python utility for managing package versions with an interactive CLI interface
Author: workingwheel
License: MIT
Project-URL: Homepage, https://github.com/workingwheel/python-package-version-manager
Project-URL: Repository, https://github.com/workingwheel/python-package-version-manager
Classifier: Programming Language :: Python :: 3.10
Classifier: Programming Language :: Python :: 3.11
Classifier: Programming Language :: Python :: 3.12
Classifier: License :: OSI Approved :: MIT License
Classifier: Operating System :: OS Independent
Requires-Python: >=3.10
Requires-Dist: rich
Requires-Dist: inquirer
Requires-Dist: packaging
